libqtile/__init__.py
libqtile/_build_config.py
libqtile/bar.py
libqtile/config.py
libqtile/configurable.py
libqtile/confreader.py
libqtile/dgroups.py
libqtile/group.py
libqtile/hook.py
libqtile/images.py
libqtile/ipc.py
libqtile/lazy.py
libqtile/log_utils.py
libqtile/notify.py
libqtile/pango_ffi.py
libqtile/pangocffi.py
libqtile/popup.py
libqtile/py.typed
libqtile/scratchpad.py
libqtile/sh.py
libqtile/utils.py
libqtile/backend/__init__.py
libqtile/backend/base/__init__.py
libqtile/backend/base/core.py
libqtile/backend/base/drawer.py
libqtile/backend/base/float_states.py
libqtile/backend/base/window.py
libqtile/backend/wayland/__init__.py
libqtile/backend/wayland/_ffi.cpython-313-x86_64-linux-gnu.so
libqtile/backend/wayland/core.py
libqtile/backend/wayland/drawer.py
libqtile/backend/wayland/ffi_stub.py
libqtile/backend/wayland/idle_inhibit.py
libqtile/backend/wayland/inputs.py
libqtile/backend/wayland/window.py
libqtile/backend/wayland/cffi/build.py
libqtile/backend/wayland/proto/wlr-layer-shell-unstable-v1.xml
libqtile/backend/wayland/proto/wlr-output-power-management-unstable-v1.xml
libqtile/backend/wayland/qw/cairo-buffer.c
libqtile/backend/wayland/qw/cairo-buffer.h
libqtile/backend/wayland/qw/cursor.c
libqtile/backend/wayland/qw/cursor.h
libqtile/backend/wayland/qw/input-device.c
libqtile/backend/wayland/qw/input-device.h
libqtile/backend/wayland/qw/internal-view.c
libqtile/backend/wayland/qw/internal-view.h
libqtile/backend/wayland/qw/keyboard.c
libqtile/backend/wayland/qw/keyboard.h
libqtile/backend/wayland/qw/layer-view.c
libqtile/backend/wayland/qw/layer-view.h
libqtile/backend/wayland/qw/log.c
libqtile/backend/wayland/qw/log.h
libqtile/backend/wayland/qw/output.c
libqtile/backend/wayland/qw/output.h
libqtile/backend/wayland/qw/server.c
libqtile/backend/wayland/qw/server.h
libqtile/backend/wayland/qw/session-lock.c
libqtile/backend/wayland/qw/session-lock.h
libqtile/backend/wayland/qw/util.c
qtile-0.34.1.dist-info/METADATA
qtile-0.34.1.dist-info/WHEEL
qtile-0.34.1.dist-info/entry_points.txt
qtile-0.34.1.dist-info/top_level.txt
qtile-0.34.1.dist-info/RECORD
qtile-0.34.1.dist-info/licenses/LICENSE
qtile-0.34.1.dist-info/sboms/auditwheel.cdx.json
