Metadata-Version: 2.4
Name: qtile
Version: 0.34.1
Summary: A pure-Python tiling window manager.
License-Expression: MIT
Project-URL: Homepage, https://qtile.org
Project-URL: Documentation, https://docs.qtile.org/
Project-URL: Code, https://github.com/qtile/qtile/
Project-URL: Issue tracker, https://github.com/qtile/qtile/issues
Project-URL: Contributing, https://docs.qtile.org/en/latest/manual/contributing.html
Classifier: Intended Audience :: End Users/Desktop
Classifier: Operating System :: POSIX :: BSD :: FreeBSD
Classifier: Operating System :: POSIX :: Linux
Classifier: Programming Language :: Python :: 3 :: Only
Classifier: Programming Language :: Python :: 3.12
Classifier: Programming Language :: Python :: 3.13
Classifier: Programming Language :: Python :: Implementation :: CPython
Classifier: Programming Language :: Python :: Implementation :: PyPy
Classifier: Topic :: Desktop Environment :: Window Managers
Requires-Python: >=3.12
License-File: LICENSE
Requires-Dist: cairocffi>=1.7.0
Requires-Dist: cffi>=1.1.0
Requires-Dist: xcffib>=1.4.0
Provides-Extra: dev
Requires-Dist: coverage; extra == "dev"
Requires-Dist: pytest-cov; extra == "dev"
Requires-Dist: pytest-asyncio>=1.1.0; extra == "dev"
Requires-Dist: pytest-httpbin; extra == "dev"
Requires-Dist: pre-commit; extra == "dev"
Requires-Dist: PyGObject; extra == "dev"
Requires-Dist: pycairo>=1.25.1; extra == "dev"
Requires-Dist: isort; extra == "dev"
Requires-Dist: pytest>=6.2.1; extra == "dev"
Requires-Dist: mypy; extra == "dev"
Requires-Dist: anyio; extra == "dev"
Requires-Dist: check-manifest; extra == "dev"
Requires-Dist: twine; extra == "dev"
Requires-Dist: build; extra == "dev"
Provides-Extra: optional-core
Requires-Dist: dbus-fast; extra == "optional-core"
Requires-Dist: libcst>=1.0.0; extra == "optional-core"
Requires-Dist: setproctitle; extra == "optional-core"
Requires-Dist: prompt_toolkit; extra == "optional-core"
Provides-Extra: widgets
Requires-Dist: imaplib2; extra == "widgets"
Requires-Dist: keyring; extra == "widgets"
Requires-Dist: mailbox; extra == "widgets"
Requires-Dist: psutil; extra == "widgets"
Requires-Dist: pulsectl; extra == "widgets"
Requires-Dist: pulsectl_asyncio; extra == "widgets"
Requires-Dist: python-mpd2; extra == "widgets"
Requires-Dist: pytz; extra == "widgets"
Requires-Dist: pyxdg; extra == "widgets"
Requires-Dist: xmltodict; extra == "widgets"
Requires-Dist: aiohttp; extra == "widgets"
Provides-Extra: docs
Requires-Dist: funcparserlib==1.0.0a0; extra == "docs"
Requires-Dist: numpydoc; extra == "docs"
Requires-Dist: libcst>=1.0.0; extra == "docs"
Requires-Dist: readthedocs-sphinx-ext; extra == "docs"
Requires-Dist: setuptools-scm>=7.0; extra == "docs"
Requires-Dist: sphinx_rtd_theme; extra == "docs"
Dynamic: license-file
